{
    "language": "en-US",
    "map": {
      "the": "ðə",
      "th": "θ",
      "sh": "ʃ",
      "ch": "tʃ",
      "ph": "f",
      "ng": "ŋ",
      "oo": "uː",
      "ee": "iː",
      "ou": "aʊ",
      "ow": "oʊ",
      "oi": "ɔɪ",
      "ar": "ɑː",
      "er": "ɜː",
      "or": "ɔː",
  
      "a": "æ",
      "b": "b",
      "c": "k",
      "d": "d",
      "e": "e",
      "f": "f",
      "g": "ɡ",
      "h": "h",
      "i": "ɪ",
      "j": "dʒ",
      "k": "k",
      "l": "l",
      "m": "m",
      "n": "n",
      "o": "ɒ",
      "p": "p",
      "q": "k",
      "r": "ɹ",
      "s": "s",
      "t": "t",
      "u": "ʌ",
      "v": "v",
      "w": "w",
      "x": "ks",
      "y": "j",
      "z": "z"
    }
  }
  